cpp_enum_class_string_idl/__init__.py
cpp_enum_class_string_idl/__main__.py
cpp_enum_class_string_idl/code_template.py
cpp_enum_class_string_idl/header_template.py
cpp_enum_class_string_idl/implementation.py
cpp_enum_class_string_idl-0.0.4.dist-info/LICENSE
cpp_enum_class_string_idl-0.0.4.dist-info/METADATA
cpp_enum_class_string_idl-0.0.4.dist-info/WHEEL
cpp_enum_class_string_idl-0.0.4.dist-info/top_level.txt
cpp_enum_class_string_idl-0.0.4.dist-info/RECORD
