Metadata-Version: 2.1
Name: cpp-enum-class-string-idl
Version: 0.0.4
Summary: cpp enum class string idl.
Home-page: https://github.com/oneofthezombies/cpp-enum-class-string-idl
Author: oneofthezombies
Author-email: hunhoekim@gmail.com
License: MIT
Platform: UNKNOWN
Classifier: Programming Language :: Python :: 3
Classifier: License :: OSI Approved :: MIT License
Classifier: Operating System :: OS Independent
Requires-Dist: pyyaml
